[{
        "id": "1",
        "name": "Test Schema 1",
        "type": 1,
        "children": [{
                "id": "2",
                "name": "Test Element 1",
                "localValues": 9,
                "allValues": 18,
                "type": 2,
                "description": "Lorem Ipsum",
                "lovLabels": ["Level 1", "Level 2", "Level 3"],
                "children": [{
                        "id": "5",
                        "name": "LOV 1",
                        "localValues": 9,
                        "allValues": 18,
                        "type": 3,
                        "children": [{
                            "id": "7",
                            "name": "LOV 3",
                            "localValues": 9,
                            "allValues": 18,
                            "type": 3,
                            "children": [{
                                "id": "8",
                                "name": "Value Element 1",
                                "localValues": 9,
                                "allValues": 18,
                                "type": 4
                            }]
                        }]
                    },
                    {
                        "isExpanded": false,
                        "id": "6",
                        "name": "Value Element 2",
                        "localValues": 9,
                        "allValues": 18,
                        "type": 4
                    }
                ]

            },
            {
                "id": "4",
                "name": "Test Element 2",
                "localValues": 9,
                "allValues": 18,
                "type": 2
            },
            {
                "id": "9",
                "name": "Test Element 3",
                "localValues": 9,
                "allValues": 18,
                "type": 2
            },
            {
                "id": "10",
                "name": "Test Element 4",
                "localValues": 9,
                "allValues": 18,
                "type": 2
            },
            {
                "id": "11",
                "name": "Test Element 5",
                "localValues": 9,
                "allValues": 18,
                "type": 2
            },
            {
                "id": "12",
                "name": "Test Element 6",
                "localValues": 9,
                "allValues": 18,
                "type": 2
            }
        ]
    },
    {
        "id": "3",
        "name": "Test Schema 2",
        "type": 1
    }
]